Metadata-Version: 1.1
Name: metaplot
Version: 1.1.0
Summary: metaplot
Home-page: https://github.com/sigvaldm/metaplot.git
Author: Sigvald Marholm
Author-email: marholm@marebakken.com
License: LGPL
Platform: UNKNOWN
Classifier: Programming Language :: Python :: 2.7
Classifier: Programming Language :: Python :: 3.5
Classifier: Programming Language :: Python :: 3.6
Classifier: Programming Language :: Python :: 3.7
